kivy_swr/__init__.py
kivy_swr/remote_data.py
kivy_swr-0.1.2.dist-info/LICENSE
kivy_swr-0.1.2.dist-info/METADATA
kivy_swr-0.1.2.dist-info/WHEEL
kivy_swr-0.1.2.dist-info/top_level.txt
kivy_swr-0.1.2.dist-info/RECORD
