Metadata-Version: 2.1
Name: kivy-swr
Version: 0.1.2
Summary: Kivy hook library for remote data fetching
Home-page: https://github.com/yanncabral/kivy-swr
Author: Yann Cabral
Author-email: iamyanndias@gmail.com
License: MIT
Download-URL: https://pypi.org/project/kivy_swr/
Keywords: swr,fetch,api,rest,axious
Platform: UNKNOWN
Requires-Dist: kivy
